{
  "parent": "aoa3:completionist/root",
  "criteria": {
    "obtain_gardener": {
      "conditions": {
        "items": [
          {
            "items": [
              "aoa3:gardener"
            ]
          }
        ]
      },
      "trigger": "minecraft:inventory_changed"
    }
  },
  "display": {
    "announce_to_chat": true,
    "description": {
      "color": "white",
      "translate": "advancements.aoa3.completionist.green_thumb.description"
    },
    "frame": "challenge",
    "hidden": false,
    "icon": {
      "item": "aoa3:gardener",
      "nbt": "{Damage:0}"
    },
    "show_toast": true,
    "title": {
      "color": "light_purple",
      "translate": "advancements.aoa3.completionist.green_thumb.title"
    }
  },
  "requirements": [
    [
      "obtain_gardener"
    ]
  ],
  "sends_telemetry_event": true
}