{
  "parent": "aoa3:completionist/root",
  "display": {
    "icon": {
      "item": "aoa3:colour_cannon",
      "nbt": "{Damage:0}"
    },
    "title": {
      "color": "light_purple",
      "translate": "advancements.aoa3.completionist.its_a_rainbow.title"
    },
    "description": {
      "color": "white",
      "translate": "advancements.aoa3.completionist.its_a_rainbow.description"
    },
    "frame": "challenge",
    "show_toast": true,
    "announce_to_chat": true,
    "hidden": true
  },
  "criteria": {
    "obtain_colour_cannon": {
      "trigger": "minecraft:inventory_changed",
      "conditions": {
        "items": [
          {
            "item": "aoa3:colour_cannon"
          }
        ]
      }
    }
  },
  "requirements": [
    [
      "obtain_colour_cannon"
    ]
  ]
}