{
  "parent": "aoa3:completionist/root",
  "criteria": {
    "level_2": {
      "conditions": {
        "level": 2
      },
      "trigger": "aoa3:level_up"
    }
  },
  "display": {
    "announce_to_chat": false,
    "description": {
      "color": "white",
      "translate": "advancements.aoa3.completionist.my_first_level.description"
    },
    "frame": "goal",
    "hidden": false,
    "icon": {
      "item": "aoa3:small_skill_crystal"
    },
    "show_toast": true,
    "title": {
      "color": "dark_green",
      "translate": "advancements.aoa3.completionist.my_first_level.title"
    }
  },
  "requirements": [
    [
      "level_2"
    ]
  ]
}