{
  "type": "minecraft:block",
  "pools": [
    {
      "rolls": 1.0,
      "bonus_rolls": {
        "type": "minecraft:uniform",
        "min": 0.0,
        "max": 0.0
      },
      "entries": [
        {
          "type": "minecraft:empty",
          "weight": 49
        },
        {
          "type": "minecraft:item",
          "name": "aoa3:purple_druse"
        }
      ],
      "conditions": [
        {
          "condition": "minecraft:inverted",
          "term": {
            "condition": "minecraft:match_tool",
            "predicate": {
              "enchantments": [
                {
                  "enchantment": "minecraft:silk_touch",
                  "levels": {
                    "min": 1
                  }
                }
              ]
            }
          }
        }
      ]
    },
    {
      "rolls": 1.0,
      "bonus_rolls": {
        "type": "minecraft:uniform",
        "min": 0.0,
        "max": 0.0
      },
      "entries": [
        {
          "type": "minecraft:item",
          "name": "aoa3:purple_crystal_plant"
        }
      ],
      "conditions": [
        {
          "condition": "minecraft:match_tool",
          "predicate": {
            "enchantments": [
              {
                "enchantment": "minecraft:silk_touch",
                "levels": {
                  "min": 1
                }
              }
            ]
          }
        }
      ]
    }
  ],
  "functions": [
    {
      "function": "minecraft:explosion_decay"
    }
  ]
}