{
  "parent": "minecraft:recipes/root",
  "rewards": {
    "recipes": [
      "aoa3:imbuing_frost_walker_ii"
    ]
  },
  "criteria": {
    "has_glowing_power_stone": {
      "trigger": "minecraft:inventory_changed",
      "conditions": {
        "items": [
          {
            "item": "aoa3:glowing_power_stone"
          }
        ]
      }
    },
    "has_magic_enhancer": {
      "trigger": "minecraft:inventory_changed",
      "conditions": {
        "items": [
          {
            "item": "aoa3:magic_enhancer"
          }
        ]
      }
    },
    "has_divine_enhancer": {
      "trigger": "minecraft:inventory_changed",
      "conditions": {
        "items": [
          {
            "item": "aoa3:divine_enhancer"
          }
        ]
      }
    },
    "has_the_recipe": {
      "trigger": "minecraft:recipe_unlocked",
      "conditions": {
        "recipe": "aoa3:imbuing_frost_walker_ii"
      }
    }
  },
  "requirements": [
    [
      "has_glowing_power_stone",
      "has_magic_enhancer",
      "has_divine_enhancer",
      "has_the_recipe"
    ]
  ]
}