{
  "type": "minecraft:fishing",
  "pools": [
    {
      "bonus_rolls": {
        "type": "minecraft:uniform",
        "max": 0.0,
        "min": 0.0
      },
      "entries": [
        {
          "type": "minecraft:item",
          "name": "minecraft:cod",
          "quality": -1,
          "weight": 100
        },
        {
          "type": "minecraft:item",
          "name": "minecraft:salmon",
          "quality": -1,
          "weight": 100
        },
        {
          "type": "minecraft:item",
          "name": "minecraft:tropical_fish",
          "quality": -1,
          "weight": 80
        },
        {
          "type": "minecraft:item",
          "name": "minecraft:pufferfish",
          "weight": 60
        },
        {
          "type": "minecraft:item",
          "name": "minecraft:nautilus_shell",
          "quality": 1,
          "weight": 20
        },
        {
          "type": "minecraft:item",
          "name": "minecraft:diamond",
          "weight": 30
        },
        {
          "type": "minecraft:item",
          "name": "minecraft:emerald",
          "quality": 2,
          "weight": 10
        },
        {
          "type": "minecraft:item",
          "name": "aoa3:rune_box",
          "quality": 1,
          "weight": 20
        },
        {
          "type": "minecraft:item",
          "name": "aoa3:shiny_box",
          "quality": 1,
          "weight": 20
        },
        {
          "type": "minecraft:item",
          "conditions": [
            {
              "condition": "aoa3:player_has_level",
              "level": 10,
              "skill": "aoa3:hauling"
            }
          ],
          "name": "aoa3:sailback",
          "weight": 75
        },
        {
          "type": "minecraft:item",
          "conditions": [
            {
              "condition": "aoa3:player_has_level",
              "level": 10,
              "skill": "aoa3:hauling"
            }
          ],
          "name": "aoa3:violet_skipper",
          "weight": 75
        },
        {
          "type": "minecraft:item",
          "conditions": [
            {
              "condition": "aoa3:player_has_level",
              "level": 10,
              "skill": "aoa3:hauling"
            }
          ],
          "name": "aoa3:raw_rainbowfish",
          "quality": 2,
          "weight": 30
        },
        {
          "type": "minecraft:item",
          "name": "aoa3:armour_plating",
          "quality": 1,
          "weight": 30
        },
        {
          "type": "minecraft:item",
          "name": "aoa3:chitin",
          "weight": 45
        },
        {
          "type": "minecraft:item",
          "name": "aoa3:chum",
          "weight": 55
        },
        {
          "type": "minecraft:item",
          "name": "minecraft:prismarine_slab",
          "weight": 40
        },
        {
          "type": "minecraft:item",
          "name": "minecraft:prismarine_crystals",
          "weight": 40
        },
        {
          "type": "minecraft:item",
          "name": "aoa3:tidal_greatblade",
          "quality": 3
        }
      ],
      "rolls": 1.0
    }
  ]
}