{
  "parent": "aoa3:lborean/lobster_mousse",
  "display": {
    "icon": {
      "item": "aoa3:gold_trophy"
    },
    "title": {
      "color": "dark_green",
      "translate": "advancements.aoa3.lborean.gold_leaf_seafood.title"
    },
    "description": {
      "color": "white",
      "translate": "advancements.aoa3.lborean.gold_leaf_seafood.description"
    },
    "frame": "task",
    "show_toast": true,
    "announce_to_chat": false,
    "hidden": false
  },
  "criteria": {
    "obtain_gold_hydrolisk_trophy": {
      "trigger": "minecraft:inventory_changed",
      "conditions": {
        "items": [
          {
            "item": "aoa3:gold_trophy",
            "nbt": "{BlockEntityTag:{EntityID:\"aoa3:hydrolisk\",OriginalTrophy:1b},display:{Name:\u0027{\"translate\":\"block.aoa3.gold_trophy.desc\",\"with\":[{\"translate\":\"entity.aoa3.hydrolisk\"}]}\u0027}}"
          }
        ]
      }
    }
  },
  "requirements": [
    [
      "obtain_gold_hydrolisk_trophy"
    ]
  ]
}