{
  "parent": "aoa3:overworld/root",
  "display": {
    "icon": {
      "item": "aoa3:penguin_slab"
    },
    "title": {
      "color": "light_purple",
      "translate": "advancements.aoa3.overworld.happy_feet.title"
    },
    "description": {
      "color": "white",
      "translate": "advancements.aoa3.overworld.happy_feet.description"
    },
    "frame": "challenge",
    "show_toast": true,
    "announce_to_chat": true,
    "hidden": true
  },
  "criteria": {
    "snowy_penguin_summon": {
      "trigger": "minecraft:impossible"
    }
  },
  "requirements": [
    [
      "snowy_penguin_summon"
    ]
  ]
}