{
  "parent": "minecraft:recipes/root",
  "rewards": {
    "recipes": [
      "aoa3:shaped_craft_armour_plating"
    ]
  },
  "criteria": {
    "has_chitin": {
      "trigger": "minecraft:inventory_changed",
      "conditions": {
        "items": [
          {
            "item": "aoa3:chitin"
          }
        ]
      }
    },
    "has_the_recipe": {
      "trigger": "minecraft:recipe_unlocked",
      "conditions": {
        "recipe": "aoa3:shaped_craft_armour_plating"
      }
    }
  },
  "requirements": [
    [
      "has_chitin",
      "has_the_recipe"
    ]
  ]
}