{
  "parent": "minecraft:recipes/root",
  "rewards": {
    "recipes": [
      "aoa3:shapeless_craft_blank_slab_from_charged_runium"
    ]
  },
  "criteria": {
    "has_charged_runium_chunk": {
      "trigger": "minecraft:inventory_changed",
      "conditions": {
        "items": [
          {
            "item": "aoa3:charged_runium_chunk"
          }
        ]
      }
    },
    "has_stone": {
      "trigger": "minecraft:inventory_changed",
      "conditions": {
        "items": [
          {
            "item": "minecraft:stone"
          }
        ]
      }
    },
    "has_the_recipe": {
      "trigger": "minecraft:recipe_unlocked",
      "conditions": {
        "recipe": "aoa3:shapeless_craft_blank_slab_from_charged_runium"
      }
    }
  },
  "requirements": [
    [
      "has_charged_runium_chunk",
      "has_stone",
      "has_the_recipe"
    ]
  ]
}